pyramid_multiauth/__init__.py
pyramid_multiauth-1.0.2.dist-info/LICENSE
pyramid_multiauth-1.0.2.dist-info/METADATA
pyramid_multiauth-1.0.2.dist-info/WHEEL
pyramid_multiauth-1.0.2.dist-info/top_level.txt
pyramid_multiauth-1.0.2.dist-info/RECORD
