Metadata-Version: 2.1
Name: pyramid_multiauth
Version: 1.0.2
Summary: An authentication policy for Pyramid that proxies to a stack of other authentication policies
Author-email: Mozilla Services <services-dev@mozilla.org>
License: Mozilla Public License Version 2.0
Project-URL: Repository, https://github.com/mozilla-services/pyramid_multiauth
Keywords: web pyramid pylons authentication
Classifier: Programming Language :: Python
Classifier: Programming Language :: Python :: 3
Classifier: Programming Language :: Python :: Implementation :: CPython
Classifier: Topic :: Internet :: WWW/HTTP
Classifier: Topic :: Internet :: WWW/HTTP :: WSGI :: Application
Classifier: Framework :: Pylons
Classifier: Development Status :: 5 - Production/Stable
Classifier: License :: OSI Approved :: Mozilla Public License 2.0 (MPL 2.0)
License-File: LICENSE
Requires-Dist: pyramid <3,>=2
Provides-Extra: dev
Requires-Dist: ruff ; extra == 'dev'
Requires-Dist: pytest ; extra == 'dev'
Requires-Dist: pytest-cache ; extra == 'dev'
Requires-Dist: pytest-cov ; extra == 'dev'
